{
    "POST /api/v2/orgauthorization/trustees/default": {
        "operationId": "postorgauthorizationtrusteesdefault",
        "functionName": "create",
        "signature": "create(assignDefaultRole, autoExpire)",
        "parameters": [
            {
                "name": "assignDefaultRole",
                "type": "bool",
                "required": "false"
            },
            {
                "name": "autoExpire",
                "type": "bool",
                "required": "false"
            }
        ],
        "return": "Trustee"
    },
    "GET /api/v2/orgauthorization/trustees/default": {
        "operationId": "getorgauthorizationtrusteesdefault",
        "functionName": "get",
        "signature": "get()",
        
        "return": "Trustee"
    }
    
}